cs/csvutils.py
cs.csvutils-20220606.dist-info/METADATA
cs.csvutils-20220606.dist-info/WHEEL
cs.csvutils-20220606.dist-info/top_level.txt
cs.csvutils-20220606.dist-info/RECORD
