Metadata-Version: 2.1
Name: cs.csvutils
Version: 20220606
Summary: CSV file related facilities
Home-page: https://bitbucket.org/cameron_simpson/css/commits/all
Author: Cameron Simpson
Author-email: Cameron Simpson <cs@cskk.id.au>
License: GNU General Public License v3 or later (GPLv3+)
Project-URL: URL, https://bitbucket.org/cameron_simpson/css/commits/all
Keywords: python2,python3
Classifier: Programming Language :: Python
Classifier: Programming Language :: Python :: 2
Classifier: Programming Language :: Python :: 3
Classifier: Development Status :: 4 - Beta
Classifier: Intended Audience :: Developers
Classifier: Operating System :: OS Independent
Classifier: Topic :: Software Development :: Libraries :: Python Modules
Classifier: License :: OSI Approved :: GNU General Public License v3 or later (GPLv3+)
Requires-Dist: cs.deco (>=20220327)
Requires-Dist: cs.logutils (>=20220531)
Requires-Dist: cs.mappings (>=20220605)
Requires-Dist: cs.pfx (>=20220523)
